{
  "source": "Cambridge",
  "url": "https://www.collinsdictionary.com/dictionary/english/determent",
  "word": "determent",
  "mp3_link": "https://www.collinsdictionary.com/sounds/hwd_sounds/15230.mp3",
  "file": null,
  "definitions": [
    "To deter someone from doing something means to make them not want to do it or continue doing it.",
    "to discourage (from acting) or prevent (from occurring), usually by instilling fear, doubt, or anxiety",
    "to keep or discourage (a person, group, or nation) from doing something by instilling fear, anxiety, doubt, etc.",
    "to discourage or restrain from acting or proceeding",
    "to prevent; check; arrest"
  ]
}