{
  "source": "Cambridge",
  "url": "https://dictionary.cambridge.org/dictionary/english/condolences",
  "word": "condolences",
  "mp3_link": "https://dictionary.cambridge.org/media/english/uk_pron/u/ukc/ukcon/ukconde020.mp3",
  "file": null,
  "definitions": [
    "sympathy and sadness for the family or close friends of a person who has recently died, or an expression of this, especially in written form:",
    "an expression of sympathy esp. for the family of a person who has recently died, or the sympathy expressed:"
  ]
}