{
  "source": "Cambridge",
  "url": "https://dictionary.cambridge.org/dictionary/english/outlay",
  "word": "outlay",
  "mp3_link": "https://dictionary.cambridge.org/media/english/uk_pron/u/uko/ukout/ukoutdo030.mp3",
  "file": null,
  "definitions": [
    "an amount of money spent for a particular purpose, especially as a first investment in something:",
    "to spend an amount of money for a particular purpose, especially as a first investment in something:",
    "an amount of money spent, esp. at the beginning of a planned activity or business:",
    "an amount of money that you spend on something, especially a large amount that is spent on new equipment or to start a new business activity:"
  ]
}